{"config": {"view": {"continuousWidth": 300, "continuousHeight": 300}, "axis": {"labelFontSize": 14, "titleFontSize": 16}, "legend": {"labelFontSize": 14, "titleFontSize": 16}, "title": {"anchor": "start", "font": "Arial", "fontSize": 20}}, "hconcat": [{"layer": [{"mark": {"type": "geoshape", "cursor": "pointer", "stroke": "black"}, "encoding": {"color": {"condition": {"param": "param_10", "field": "total_items", "legend": {"orient": "bottom"}, "scale": {"range": ["#EEEEEE", "#0AC0AD"]}, "title": "Total Items", "type": "quantitative"}, "value": "white"}, "tooltip": [{"field": "region_label", "title": "Region", "type": "nominal"}, {"field": "total_items", "title": "Total Items", "type": "quantitative"}]}, "name": "view_10", "projection": {"type": "mercator"}, "transform": [{"calculate": "datum.properties.reg_name == \"Trentino-Alto Adige/S\u00fcdtirol\" ? \"Trentino Alto Adige\" : datum.properties.reg_name == \"Valle d'Aosta/Vall\u00e9e d'Aoste\" ? \"Val d'Aosta\" : datum.properties.reg_name", "as": "region_label"}, {"lookup": "region_label", "from": {"data": {"name": "data-374cef79bab9fa88dca5b206b6817ebb"}, "key": "region_label", "fields": ["total_items"]}}]}, {"mark": {"type": "geoshape", "fill": null, "stroke": "black", "strokeWidth": 1}, "projection": {"type": "mercator"}}], "data": {"url": "https://raw.githubusercontent.com/openpolis/geojson-italy/master/topojson/limits_IT_all.topo.json", "format": {"feature": "regions", "type": "topojson"}}, "height": 350, "width": 250}, {"data": {"name": "data-aa2ab57ca491bd006b523ece69ead322"}, "mark": {"type": "bar"}, "encoding": {"color": {"value": "#0AC0AD"}, "tooltip": [{"field": "seller_class", "title": "Seller Class", "type": "nominal"}, {"field": "n_items", "title": "Items Published", "type": "quantitative"}, {"field": "n_users", "title": "Number of Sellers", "type": "quantitative"}], "x": {"field": "n_items", "title": "Number of Items Published", "type": "quantitative"}, "y": {"field": "seller_class", "sort": ["Casual & Low Seller", "Mid Seller", "Power Seller", "Super Seller"], "title": null, "type": "nominal"}}, "height": 280, "transform": [{"filter": {"param": "param_10"}}], "width": 350}], "params": [{"name": "param_10", "select": {"type": "point", "fields": ["region_label"]}, "views": ["view_10"]}], "resolve": {"scale": {"color": "independent"}}, "$schema": "https://vega.github.io/schema/vega-lite/v5.20.1.json", "datasets": {"data-374cef79bab9fa88dca5b206b6817ebb": [{"region_label": "Abruzzo", "total_items": 5204}, {"region_label": "Basilicata", "total_items": 1897}, {"region_label": "Calabria", "total_items": 5555}, {"region_label": "Campania", "total_items": 56384}, {"region_label": "Emilia-Romagna", "total_items": 25529}, {"region_label": "Friuli-Venezia Giulia", "total_items": 3749}, {"region_label": "Lazio", "total_items": 34336}, {"region_label": "Liguria", "total_items": 5358}, {"region_label": "Lombardia", "total_items": 45994}, {"region_label": "Marche", "total_items": 6987}, {"region_label": "Molise", "total_items": 829}, {"region_label": "Piemonte", "total_items": 18639}, {"region_label": "Puglia", "total_items": 25950}, {"region_label": "Sardegna", "total_items": 4256}, {"region_label": "Sicilia", "total_items": 20540}, {"region_label": "Toscana", "total_items": 18000}, {"region_label": "Trentino Alto Adige", "total_items": 3168}, {"region_label": "Umbria", "total_items": 5963}, {"region_label": "Unknown", "total_items": 142180}, {"region_label": "Val d'Aosta", "total_items": 197}, {"region_label": "Veneto", "total_items": 18866}], "data-aa2ab57ca491bd006b523ece69ead322": [{"region_label": "Abruzzo", "seller_class": "Casual & Low Seller", "n_items": 4352, "n_users": 2891}, {"region_label": "Abruzzo", "seller_class": "Mid Seller", "n_items": 620, "n_users": 77}, {"region_label": "Abruzzo", "seller_class": "Power Seller", "n_items": 232, "n_users": 4}, {"region_label": "Basilicata", "seller_class": "Casual & Low Seller", "n_items": 1535, "n_users": 1014}, {"region_label": "Basilicata", "seller_class": "Mid Seller", "n_items": 330, "n_users": 34}, {"region_label": "Basilicata", "seller_class": "Power Seller", "n_items": 32, "n_users": 1}, {"region_label": "Calabria", "seller_class": "Casual & Low Seller", "n_items": 4321, "n_users": 2769}, {"region_label": "Calabria", "seller_class": "Mid Seller", "n_items": 1129, "n_users": 121}, {"region_label": "Calabria", "seller_class": "Power Seller", "n_items": 105, "n_users": 2}, {"region_label": "Campania", "seller_class": "Casual & Low Seller", "n_items": 37425, "n_users": 22491}, {"region_label": "Campania", "seller_class": "Mid Seller", "n_items": 15104, "n_users": 1542}, {"region_label": "Campania", "seller_class": "Power Seller", "n_items": 3855, "n_users": 73}, {"region_label": "Emilia-Romagna", "seller_class": "Casual & Low Seller", "n_items": 21319, "n_users": 14224}, {"region_label": "Emilia-Romagna", "seller_class": "Mid Seller", "n_items": 3649, "n_users": 401}, {"region_label": "Emilia-Romagna", "seller_class": "Power Seller", "n_items": 561, "n_users": 9}, {"region_label": "Friuli-Venezia Giulia", "seller_class": "Casual & Low Seller", "n_items": 3270, "n_users": 2227}, {"region_label": "Friuli-Venezia Giulia", "seller_class": "Mid Seller", "n_items": 339, "n_users": 43}, {"region_label": "Friuli-Venezia Giulia", "seller_class": "Power Seller", "n_items": 140, "n_users": 2}, {"region_label": "Lazio", "seller_class": "Casual & Low Seller", "n_items": 28182, "n_users": 18539}, {"region_label": "Lazio", "seller_class": "Mid Seller", "n_items": 4949, "n_users": 555}, {"region_label": "Lazio", "seller_class": "Power Seller", "n_items": 1205, "n_users": 27}, {"region_label": "Liguria", "seller_class": "Casual & Low Seller", "n_items": 4668, "n_users": 3231}, {"region_label": "Liguria", "seller_class": "Mid Seller", "n_items": 652, "n_users": 73}, {"region_label": "Liguria", "seller_class": "Power Seller", "n_items": 38, "n_users": 1}, {"region_label": "Lombardia", "seller_class": "Casual & Low Seller", "n_items": 39118, "n_users": 26499}, {"region_label": "Lombardia", "seller_class": "Mid Seller", "n_items": 5798, "n_users": 656}, {"region_label": "Lombardia", "seller_class": "Power Seller", "n_items": 1078, "n_users": 19}, {"region_label": "Marche", "seller_class": "Casual & Low Seller", "n_items": 6043, "n_users": 4178}, {"region_label": "Marche", "seller_class": "Mid Seller", "n_items": 882, "n_users": 96}, {"region_label": "Marche", "seller_class": "Power Seller", "n_items": 62, "n_users": 2}, {"region_label": "Molise", "seller_class": "Casual & Low Seller", "n_items": 752, "n_users": 514}, {"region_label": "Molise", "seller_class": "Mid Seller", "n_items": 77, "n_users": 8}, {"region_label": "Piemonte", "seller_class": "Casual & Low Seller", "n_items": 15114, "n_users": 10288}, {"region_label": "Piemonte", "seller_class": "Mid Seller", "n_items": 2748, "n_users": 292}, {"region_label": "Piemonte", "seller_class": "Power Seller", "n_items": 777, "n_users": 17}, {"region_label": "Puglia", "seller_class": "Casual & Low Seller", "n_items": 19755, "n_users": 12615}, {"region_label": "Puglia", "seller_class": "Mid Seller", "n_items": 4665, "n_users": 493}, {"region_label": "Puglia", "seller_class": "Power Seller", "n_items": 1530, "n_users": 25}, {"region_label": "Sardegna", "seller_class": "Casual & Low Seller", "n_items": 3613, "n_users": 2423}, {"region_label": "Sardegna", "seller_class": "Mid Seller", "n_items": 541, "n_users": 62}, {"region_label": "Sardegna", "seller_class": "Power Seller", "n_items": 102, "n_users": 2}, {"region_label": "Sicilia", "seller_class": "Casual & Low Seller", "n_items": 15314, "n_users": 9896}, {"region_label": "Sicilia", "seller_class": "Mid Seller", "n_items": 3806, "n_users": 414}, {"region_label": "Sicilia", "seller_class": "Power Seller", "n_items": 1420, "n_users": 26}, {"region_label": "Toscana", "seller_class": "Casual & Low Seller", "n_items": 14713, "n_users": 9871}, {"region_label": "Toscana", "seller_class": "Mid Seller", "n_items": 2588, "n_users": 288}, {"region_label": "Toscana", "seller_class": "Power Seller", "n_items": 699, "n_users": 12}, {"region_label": "Trentino Alto Adige", "seller_class": "Casual & Low Seller", "n_items": 2862, "n_users": 1952}, {"region_label": "Trentino Alto Adige", "seller_class": "Mid Seller", "n_items": 306, "n_users": 33}, {"region_label": "Umbria", "seller_class": "Casual & Low Seller", "n_items": 4268, "n_users": 2693}, {"region_label": "Umbria", "seller_class": "Mid Seller", "n_items": 1363, "n_users": 127}, {"region_label": "Umbria", "seller_class": "Power Seller", "n_items": 332, "n_users": 6}, {"region_label": "Unknown", "seller_class": "Casual & Low Seller", "n_items": 86982, "n_users": 54170}, {"region_label": "Unknown", "seller_class": "Mid Seller", "n_items": 31859, "n_users": 3223}, {"region_label": "Unknown", "seller_class": "Power Seller", "n_items": 13463, "n_users": 234}, {"region_label": "Unknown", "seller_class": "Super Seller", "n_items": 9876, "n_users": 9}, {"region_label": "Val d'Aosta", "seller_class": "Casual & Low Seller", "n_items": 190, "n_users": 138}, {"region_label": "Val d'Aosta", "seller_class": "Mid Seller", "n_items": 7, "n_users": 1}, {"region_label": "Veneto", "seller_class": "Casual & Low Seller", "n_items": 16068, "n_users": 10862}, {"region_label": "Veneto", "seller_class": "Mid Seller", "n_items": 2456, "n_users": 280}, {"region_label": "Veneto", "seller_class": "Power Seller", "n_items": 342, "n_users": 7}]}}